alagitpull/__init__.py
alagitpull/_version.py
alagitpull/more.html
alagitpull/static/alagitpull.css_t
alagitpull/theme.conf
alagitpull/writers/__init__.py
alagitpull/writers/external.py
alagitpull-0.1.0.dist-info/entry_points.txt
alagitpull-0.1.0.dist-info/LICENSE
alagitpull-0.1.0.dist-info/WHEEL
alagitpull-0.1.0.dist-info/METADATA
alagitpull-0.1.0.dist-info/RECORD
