Metadata-Version: 2.1
Name: alagitpull
Version: 0.1.0
Summary: Cleverly-named alabaster sub-theme for git-pull projects
Home-page: https://github.com/git-pull/alagitpull
License: MIT
Keywords: sphinx,theme,sphinx-theme,alabaster
Author: Tony Narlock
Author-email: tony@git-pull.com
Requires-Python: >=2.7, !=3.0.*, !=3.1.*, !=3.2.*, !=3.3.*, !=3.4.*
Classifier: Development Status :: 4 - Beta
Classifier: Environment :: Web Environment
Classifier: Intended Audience :: Developers
Classifier: License :: OSI Approved :: MIT License
Classifier: Operating System :: OS Independent
Classifier: Programming Language :: Python
Classifier: Programming Language :: Python :: 2
Classifier: Programming Language :: Python :: 2.7
Classifier: Programming Language :: Python :: 3
Classifier: Programming Language :: Python :: 3.5
Classifier: Programming Language :: Python :: 3.6
Classifier: Programming Language :: Python :: 3.7
Classifier: Programming Language :: Python :: 3.8
Classifier: Programming Language :: Python :: Implementation :: PyPy
Classifier: Topic :: Documentation
Classifier: Topic :: Software Development :: Documentation
Requires-Dist: alabaster (<0.8)
Project-URL: Bug Tracker, https://github.com/git-pull/alagitpull/issues
Project-URL: Documentation, https://github.com/git-pull/alagitpull
Project-URL: Repository, https://github.com/git-pull/alagitpull
